{
  "type": "mysql",
  "host": "localhost",
  "port": 3306,
  "username": "admin",
  "password": "secret",
  "database": "default",
  "entities": ["dist/entity/**/*{.js,.ts}"],
  "migrations": ["dist/database/migration/**/*{.js,.ts}"],
  "seeds": ["dist/database/seeder/*.js"],
  "factories": ["dist/database/factory/*.js"],
  "synchronize": false,
  "cli": {
    "entitiesDir": "src/entity",
    "migrationsDir": "src/database/migration",
    "seedersDir": "src/database/seeder",
    "factoriesDir": "src/database/factory"
  }
}
